LICENSE
README.md
setup.py
bandolier/__init__.py
bandolier/annotations.py
bandolier/bandolier.py
bandolier/conversation.py
bandolier.egg-info/PKG-INFO
bandolier.egg-info/SOURCES.txt
bandolier.egg-info/dependency_links.txt
bandolier.egg-info/requires.txt
bandolier.egg-info/top_level.txt