Metadata-Version: 2.1
Name: bandolier
Version: 0.1.3
Summary: A helper for OpenAI functions
Home-page: https://github.com/johnnysands/bandolier
Author: Johnny Sands
Author-email: johnnysands@users.noreply.github.com
License: MIT
Classifier: Development Status :: 5 - Production/Stable
Classifier: Intended Audience :: Science/Research
Classifier: License :: OSI Approved :: MIT License
Classifier: Operating System :: POSIX :: Linux
Classifier: Programming Language :: Python :: 3
Classifier: Operating System :: MacOS :: MacOS X
Classifier: Operating System :: Microsoft :: Windows
Provides-Extra: dev
License-File: LICENSE
